gridtools/__info__.py
gridtools/__init__.py
gridtools/__main__.py
gridtools/gridtools.py
gridtools/py.typed
gridtools-1.0.0.post1.dist-info/LICENSE
gridtools-1.0.0.post1.dist-info/METADATA
gridtools-1.0.0.post1.dist-info/WHEEL
gridtools-1.0.0.post1.dist-info/top_level.txt
gridtools-1.0.0.post1.dist-info/RECORD
