Metadata-Version: 2.1
Name: gridtools
Version: 1.0.0.post1
Summary: A small Python library to convert between maidenhead grid locators and lat/long coördinates.
Home-page: https://gridtools.miaow.io/
Author: classabbyamp, 0x5c
Author-email: dev@kb6.ee, dev@0x5c.io
License: BSD 3-Clause
Platform: UNKNOWN
Classifier: Programming Language :: Python :: 3
Classifier: Programming Language :: Python :: 3.8
Classifier: Programming Language :: Python :: 3.9
Classifier: License :: OSI Approved :: BSD License
Classifier: Operating System :: OS Independent
Classifier: Development Status :: 5 - Production/Stable
Classifier: Environment :: Console
Classifier: Intended Audience :: Science/Research
Classifier: Topic :: Communications :: Ham Radio
